hello_world/__init__.py
hello_world/hello.py
joaomarcosbraz-0.1.1.dist-info/METADATA
joaomarcosbraz-0.1.1.dist-info/WHEEL
joaomarcosbraz-0.1.1.dist-info/top_level.txt
joaomarcosbraz-0.1.1.dist-info/RECORD
