Metadata-Version: 2.1
Name: joaomarcosbraz
Version: 0.1.1
Summary: Um simples pacote de Hello World
Home-page: 
Author: João Marcos Braz
Author-email: jbrazm.dev@gmail.com
Classifier: Programming Language :: Python :: 3
Classifier: License :: OSI Approved :: MIT License
Classifier: Operating System :: OS Independent
Requires-Python: >=3.6
